ejson/__init__.py
mongodb_ejson-1.0.1.dist-info/LICENSE
mongodb_ejson-1.0.1.dist-info/METADATA
mongodb_ejson-1.0.1.dist-info/WHEEL
mongodb_ejson-1.0.1.dist-info/top_level.txt
mongodb_ejson-1.0.1.dist-info/RECORD
