Metadata-Version: 2.1
Name: mongodb-ejson
Version: 1.0.1
Summary: Encoder and Decoder for Extended JSON (EJSON) as used in MongoDB
Home-page: https://github.com/Sojo-uk/meteor-ejson-python
Author: Isaac Rego
Author-email: isaac.rego@sojo.uk
License: MIT
Platform: UNKNOWN
Classifier: Environment :: Web Environment
Classifier: Intended Audience :: Developers
Classifier: License :: OSI Approved :: MIT License
Classifier: Operating System :: OS Independent
Classifier: Programming Language :: Python
Classifier: Programming Language :: Python :: 2.7
Classifier: Programming Language :: Python :: 3
Classifier: Programming Language :: Python :: 3.3
Classifier: Programming Language :: Python :: 3.4
Classifier: Topic :: Internet :: WWW/HTTP
Classifier: Topic :: Software Development :: Libraries :: Python Modules
Requires-Dist: six
